tetry/__init__.py
tetry/badges.py
tetry/base.py
tetry/endcontext.py
tetry/example.py
tetry/records.py
tetry/tetraLeauge.py
tetry/urls.py
tetry/user.py
tetry/api/__init__.py
tetry/api/cache.py
tetry/api/commitId.py
tetry/api/news.py
tetry/api/records.py
tetry/api/resolve.py
tetry/api/stream.py
tetry/api/urls.py
tetry/api/user.py
tetry/bot/__init__.py
tetry/bot/bot.py
tetry/bot/chatCommands.py
tetry/bot/chatMessage.py
tetry/bot/commandChecks.py
tetry/bot/commands.py
tetry/bot/dm.py
tetry/bot/events.py
tetry/bot/frame.py
tetry/bot/friend.py
tetry/bot/game.py
tetry/bot/hypertap.py
tetry/bot/invite.py
tetry/bot/message.py
tetry/bot/notification.py
tetry/bot/pieceRng.py
tetry/bot/reconnect.py
tetry/bot/responses.py
tetry/bot/ribbons.py
tetry/bot/room.py
tetry/bot/urls.py
tetry/bot/engine/__init__.py
tetry/bot/engine/board.py
tetry/bot/engine/game.py
tetry/bot/engine/piece.py
tetry/bot/engine/pieceRng.py
tetry/bot/engine/pieces.py
tetry/bot/engine/spawnLocation.py
tetry/bot/engine/srs.py
tetry/bot/tools/__init__.py
tetry/bot/tools/anon.py
tetry/bot/tools/urls.py
tetry/oldApi/__init__.py
tetry/oldApi/badges.py
tetry/oldApi/base.py
tetry/oldApi/endcontext.py
tetry/oldApi/records.py
tetry/oldApi/tetraLeauge.py
tetry/oldApi/urls.py
tetry/oldApi/user.py
tetry-1.3.2.dist-info/LICENSE
tetry-1.3.2.dist-info/METADATA
tetry-1.3.2.dist-info/WHEEL
tetry-1.3.2.dist-info/top_level.txt
tetry-1.3.2.dist-info/RECORD
