Metadata-Version: 2.1
Name: tetry
Version: 1.3.2
Summary: tetr.io api wrapper
Home-page: https://github.com/apes0/tetry
Author: apes0
License: GPLv3
Project-URL: Source, https://github.com/apes0/tetry
Project-URL: Tracker, https://github.com/apes0/tetry/issues
Platform: UNKNOWN
Requires-Python: >=3.6
License-File: LICENSE
Requires-Dist: trio
Requires-Dist: requests
Requires-Dist: trio-websocket
Requires-Dist: msgpack
